Metadata-Version: 2.1
Name: slackbot-newsletter-deschamps
Version: 1.0.1
Summary: Slackbot Tech Newsletter from e-mail
Home-page: https://github.com/alexandremendoncaalvaro/slackbot-newsletter-deschamps
Author: Alexandre Alvaro
Author-email: alexandre.alvaro@hotmail.com
License: MIT License
Keywords: Pacote
Platform: UNKNOWN
Classifier: Programming Language :: Python :: 3
Classifier: License :: OSI Approved :: MIT License
Classifier: Operating System :: OS Independent
Requires-Python: >=3.8
License-File: LICENSE
